{
  "descriptors": {
    "components": [
      {
        "id": "irc",
        "component": "source",
        "type": "irc",
        "name": "IRC Source",
        "description": "Connect IRC channels and retrieve messages from them.",
        "settings": {
          "hostname": {
            "type": "string",
            "name": "Host name",
            "description": "Target URI",
            "default": "",
            "required": true
          },
          "port": {
            "type": "integer",
            "name": "Port",
            "description": "IRC port",
            "default": 6667,
            "required": true
          },
          "nick": {
            "type": "string",
            "name": "Nick",
            "description": "Nickname",
            "default": "",
            "required": true
          },
          "channels": {
            "type": "string",
            "name": "Channels",
            "description": "Comma separated channels without hash. Example: ubuntu, trivial.",
            "default": "",
            "required": true
          },
          "user": {
            "type": "string",
            "name": "User",
            "description": "The username. Is used to register the connection.",
            "default": "",
            "required": false
          },
          "name": {
            "type": "string",
            "name": "Name",
            "description": "The realname. Is used to register the connection.",
            "default": "",
            "required": false
          },
          "password": {
            "type": "string",
            "name": "Capacity",
            "description": "Password. Required if you are registered.",
            "default": "",
            "required": false
          },
          "replyPing": {
            "type": "boolean",
            "name": "Reply ping",
            "description": "Automatically sends pong when receives a ping.",
            "default": "false",
            "required": false
          }
        },
        "ports": {

        },
        "ui": {

        }
      }
    ]
  }
}